psequant/__init__.py
psequant/psequant.py
psequant-0.1.2.4.dist-info/LICENSE
psequant-0.1.2.4.dist-info/METADATA
psequant-0.1.2.4.dist-info/WHEEL
psequant-0.1.2.4.dist-info/top_level.txt
psequant-0.1.2.4.dist-info/RECORD
