Metadata-Version: 2.1
Name: psequant
Version: 0.1.2.4
Summary: The easiest way to access and analyze Philippine stock data
Home-page: https://github.com/enzoampil/psequant
Author: Lorenzo Ampil
Author-email: lorenzo.ampil@gmail.com
License: UNKNOWN
Platform: UNKNOWN
Classifier: Programming Language :: Python :: 3
Classifier: License :: OSI Approved :: GNU General Public License v3 (GPLv3)
Classifier: Operating System :: OS Independent
Requires-Dist: backtrader (==1.9.74.123)
Requires-Dist: beautifulsoup4 (==4.8.2)
Requires-Dist: black (==19.10b0)
Requires-Dist: bs4 (==0.0.1)
Requires-Dist: certifi (==2019.11.28)
Requires-Dist: chardet (==3.0.4)
Requires-Dist: idna (==2.8)
Requires-Dist: lxml (==4.4.2)
Requires-Dist: matplotlib (==3.1.2)
Requires-Dist: numpy (==1.18.0)
Requires-Dist: oauthlib (==3.1.0)
Requires-Dist: pandas (==0.25.3)
Requires-Dist: PySocks (==1.7.1)
Requires-Dist: python-dateutil (==2.8.1)
Requires-Dist: pytz (==2019.3)
Requires-Dist: requests (==2.22.0)
Requires-Dist: requests-oauthlib (==1.3.0)
Requires-Dist: six (==1.13.0)
Requires-Dist: soupsieve (==1.9.5)
Requires-Dist: tweepy (==3.8.0)
Requires-Dist: urllib3 (==1.25.7)
